db4sphinx/__init__.py
db4sphinx/dbparser.py
db4sphinx/ext.py
db4sphinx/scripts.py
db4sphinx-0.1.1.dist-info/DESCRIPTION.rst
db4sphinx-0.1.1.dist-info/METADATA
db4sphinx-0.1.1.dist-info/RECORD
db4sphinx-0.1.1.dist-info/WHEEL
db4sphinx-0.1.1.dist-info/entry_points.txt
db4sphinx-0.1.1.dist-info/metadata.json
db4sphinx-0.1.1.dist-info/top_level.txt
