Metadata-Version: 2.0
Name: db4sphinx
Version: 0.1.1
Summary: Docbook parser for docutils and sphinx
Home-page: https://github.com/bonzini/db4sphinx
Author: Paolo Bonzini
Author-email: pbonzini@redhat.com
License: MIT
Keywords: sphinx docbook xml
Platform: UNKNOWN
Classifier: Development Status :: 3 - Alpha
Classifier: Intended Audience :: Developers
Classifier: Topic :: Software Development :: Build Tools
Classifier: License :: OSI Approved :: MIT License
Classifier: Programming Language :: Python :: 2
Classifier: Programming Language :: Python :: 2.7
Classifier: Programming Language :: Python :: 3
Classifier: Programming Language :: Python :: 3.5
Requires-Dist: sphinx
Requires-Dist: lxml
